accuknox_llm_defense/__init__.py
accuknox_llm_defense/client.py
accuknox_llm_defense-0.1.3.dist-info/METADATA
accuknox_llm_defense-0.1.3.dist-info/WHEEL
accuknox_llm_defense-0.1.3.dist-info/top_level.txt
accuknox_llm_defense-0.1.3.dist-info/RECORD
