Metadata-Version: 2.4
Name: accuknox-llm-defense
Version: 0.1.3
Summary: Python SDK for AccuKnox LLM Defence API
Home-page: https://github.com/yourusername/accuknox-llm-defense
Author: Yash Sanjay Kulkarni
Author-email: yashkulkarni2023@gmail.com
Classifier: Programming Language :: Python :: 3
Classifier: Operating System :: OS Independent
Requires-Python: >=3.7
Requires-Dist: requests>=2.20.0
Requires-Dist: pyjwt>=2.3.0
Dynamic: author
Dynamic: author-email
Dynamic: classifier
Dynamic: home-page
Dynamic: requires-dist
Dynamic: requires-python
Dynamic: summary
